zlm/__init__.py
zlm/demo_data/user_profile.json
zlm/demo_data/user_resume.pdf
zlm/prompts/resume_prompt.py
zlm/prompts/sections_prompt.py
zlm/schemas/job_details_schema.py
zlm/schemas/sections_schemas.py
zlm/templates/resume.cls
zlm/templates/resume.tex.jinja
zlm/utils/data_extraction.py
zlm/utils/latex_ops.py
zlm/utils/llm_models.py
zlm/utils/metrics.py
zlm/utils/utils.py
zlm/variables.py
zlm-0.1.35.dist-info/LICENSE
zlm-0.1.35.dist-info/METADATA
zlm-0.1.35.dist-info/WHEEL
zlm-0.1.35.dist-info/RECORD
