Metadata-Version: 2.1
Name: zlm
Version: 0.1.35
Summary: Simplify and improve your job hunting experience by integrating LLMs to automate tasks such as resume and cover letter generation, as well as application submission, saving users time and effort.
Author: Saurabh Zinjad
Author-email: zinjadsaurabh1997@gmail.com
Requires-Python: >=3.11.6,<3.13
Classifier: Programming Language :: Python :: 3
Classifier: Programming Language :: Python :: 3.12
Requires-Dist: beautifulsoup4 (>=4.12.3,<5.0.0)
Requires-Dist: fpdf (>=1.7.2,<2.0.0)
Requires-Dist: google-generativeai (>=0.7.2,<0.8.0)
Requires-Dist: langchain-community (>=0.2.12,<0.3.0)
Requires-Dist: langchain-core (>=0.2.33,<0.3.0)
Requires-Dist: langchain-ollama (>=0.1.1,<0.2.0)
Requires-Dist: nltk (>=3.8.1,<4.0.0)
Requires-Dist: openai (>=1.41.0,<2.0.0)
Requires-Dist: pdf2image (>=1.17.0,<2.0.0)
Requires-Dist: playwright (>=1.46.0,<2.0.0)
Requires-Dist: pypdf2 (>=3.0.1,<4.0.0)
Requires-Dist: scikit-learn (>=1.5.1,<2.0.0)
Requires-Dist: streamlit (>=1.37.1,<2.0.0)
Requires-Dist: unstructured (>=0.15.5,<0.16.0)
Requires-Dist: validators (>=0.33.0,<0.34.0)
